raven_gen/__init__.py
raven_gen/attribute.py
raven_gen/component.py
raven_gen/entity.py
raven_gen/matrix.py
raven_gen/panel.py
raven_gen/rule.py
raven_gen-0.3.2.dist-info/LICENSE
raven_gen-0.3.2.dist-info/METADATA
raven_gen-0.3.2.dist-info/WHEEL
raven_gen-0.3.2.dist-info/top_level.txt
raven_gen-0.3.2.dist-info/RECORD
