Metadata-Version: 2.1
Name: raven-gen
Version: 0.3.2
Summary: A tool for programmatic and customizable generation of Raven's Progressive Matrices in the style of the RAVEN dataset
Author-email: Eli Whitehouse <eliw55@gmail.com>
Project-URL: Homepage, https://github.com/shlomenu/raven-gen
Classifier: Programming Language :: Python :: 3
Classifier: License :: OSI Approved :: GNU General Public License v3 (GPLv3)
Classifier: Operating System :: OS Independent
Classifier: Topic :: Scientific/Engineering :: Image Recognition
Classifier: Topic :: Scientific/Engineering :: Artificial Intelligence
Requires-Python: >=3.8
License-File: LICENSE
Requires-Dist: numpy
Requires-Dist: scipy
Requires-Dist: pillow
Requires-Dist: opencv-python
